LICENSE
README.md
setup.cfg
setup.py
botasaurus_server/__init__.py
botasaurus_server/app.py
botasaurus_server/apply_pagination.py
botasaurus_server/check_node.py
botasaurus_server/cleaners.py
botasaurus_server/controls_adapter.py
botasaurus_server/convert_to_english.py
botasaurus_server/db_setup.py
botasaurus_server/download.py
botasaurus_server/env.py
botasaurus_server/errors.py
botasaurus_server/executor.py
botasaurus_server/filters.py
botasaurus_server/filters_export.py
botasaurus_server/k8s.py
botasaurus_server/master_executor.py
botasaurus_server/master_routes.py
botasaurus_server/models.py
botasaurus_server/port_kill_adapter.py
botasaurus_server/retry_on_db_error.py
botasaurus_server/routes_db_logic.py
botasaurus_server/run.py
botasaurus_server/scraper_type.py
botasaurus_server/server.py
botasaurus_server/sort_export.py
botasaurus_server/sorts.py
botasaurus_server/task_executor.py
botasaurus_server/task_helper.py
botasaurus_server/task_results.py
botasaurus_server/task_routes.py
botasaurus_server/ui.py
botasaurus_server/utils.py
botasaurus_server/validation.py
botasaurus_server/views.py
botasaurus_server/worker_executor.py
botasaurus_server/worker_routes.py
botasaurus_server.egg-info/PKG-INFO
botasaurus_server.egg-info/SOURCES.txt
botasaurus_server.egg-info/dependency_links.txt
botasaurus_server.egg-info/requires.txt
botasaurus_server.egg-info/top_level.txt