Metadata-Version: 2.4
Name: botasaurus_server
Version: 4.0.61
Summary: Botasaurus Server allows you to transform your scrapers into APIs or scale them using Kubernetes.
Home-page: https://github.com/omkarcloud/botasaurus
Author: Chetan Jain
Author-email: 53407137+Chetan11-dev@users.noreply.github.com
License: MIT
Keywords: botasaurus,botasaurus_server
Classifier: Development Status :: 5 - Production/Stable
Classifier: Topic :: Software Development :: Testing
Classifier: Topic :: System :: Installation/Setup
Classifier: Topic :: Software Development :: Libraries :: Python Modules
Classifier: License :: OSI Approved :: MIT License
Classifier: Programming Language :: Python :: 3
Classifier: Programming Language :: Python :: 3.6
Classifier: Programming Language :: Python :: 3.7
Classifier: Programming Language :: Python :: 3.8
Classifier: Programming Language :: Python :: 3.9
Classifier: Programming Language :: Python :: 3.10
Requires-Python: >=3.6
License-File: LICENSE
Requires-Dist: Unidecode
Requires-Dist: ndjson
Requires-Dist: casefy
Requires-Dist: bottle
Requires-Dist: kubernetes
Requires-Dist: xlsxwriter
Requires-Dist: sqlalchemy
Dynamic: author
Dynamic: author-email
Dynamic: classifier
Dynamic: description
Dynamic: description-content-type
Dynamic: home-page
Dynamic: keywords
Dynamic: license
Dynamic: license-file
Dynamic: requires-dist
Dynamic: requires-python
Dynamic: summary
